inworld_sdk/__init__.py
inworld_sdk/http_wrapper.py
inworld_sdk/models.py
inworld_sdk/py.typed
inworld_sdk/tts.py
inworld_sdk-0.7.0.dist-info/licenses/LICENSE.md
inworld_sdk-0.7.0.dist-info/METADATA
inworld_sdk-0.7.0.dist-info/WHEEL
inworld_sdk-0.7.0.dist-info/top_level.txt
inworld_sdk-0.7.0.dist-info/RECORD
