Metadata-Version: 2.4
Name: inworld-sdk
Version: 0.7.0
Summary: A Python SDK for Inworld
Author-email: Michael Solati <mkslt04@gmail.com>
Project-URL: Homepage, https://github.com/MichaelSolati/inworld-sdk-python
Project-URL: Bug Tracker, https://github.com/MichaelSolati/inworld-sdk-python/issues
Classifier: Programming Language :: Python :: 3
Classifier: License :: OSI Approved :: MIT License
Classifier: Operating System :: OS Independent
Requires-Python: >=3.9
License-File: LICENSE.md
Requires-Dist: httpx>=0.28.1
Provides-Extra: dev
Requires-Dist: black>=25.1; extra == "dev"
Requires-Dist: isort>=6.0; extra == "dev"
Requires-Dist: flake8>=7.2; extra == "dev"
Requires-Dist: mypy>=1.16; extra == "dev"
Dynamic: license-file
